{
  "keywords": {
    "啊啊啊": ["啊什么？", "啊啊啊～吓我一跳！", "不要啊！"],
    "早上好": ["早啊", "这么早呀", "吃早餐了吗"],
    "中午好": ["中午好", "吃午饭了吗", "中午不午睡吗"],
    "晚上好": ["晚上好", "吃晚饭了吗", "晚上坏"],
    "谢谢": ["不客气", "客气了", "不用谢"],
    "好台": ["好个锤子哦", "抠得要死", "88都不舍得送"],
    "吃饭": ["@rouououou 妈妈有人喊你", "@rouououou 主银有叼毛叫你呢", "@rouououou 宝宝有人找你"],
    "妞妞": ["@niuniu9393 宝贝有猪叫你", "@niuniu9393 宝宝有人找你", "@niuniu9393 宝子那个谁喊你"],
    "小点": ["@Xdianer 小祖宗有猪喊你", "@Xdianer 小祖宗有人叫你", "@Xdianer 小祖宗有叼毛找你"],
    "稳台": ["稳个锤子", "有多稳啊", "稳你奶奶的腿"],
    "baby": ["@xiaomeidian 妈咪，二傻蛋找你嘞", "@xiaomeidian 妈妈咪，隔壁老王找你诶", "@xiaomeidian 妈呀，二狗子来啦"],
    "小美": ["@xinginging 老婆，狗子找你嘞", "@xinginging 脑婆，有坏人喊你呢", "@xinginging 宝宝，快跑色批叫你啦"],
    "我勒个豆": ["我嘞个骚刚", "豆什么豆啊", "豆你奶奶的腿"],
    "我嘞个豆": ["我嘞个骚刚", "哪有豆啊", "你有很多痘？"],
    "牛逼": ["我肯定牛逼", "牛批plus", "有多牛逼？"],
    "刷抖音": ["又在抖音看扭屁股？", "别刷了来聊天呀", "刷抖音就是堕落，废了呀"],
    "啦啦啦": ["我是卖报的小行家", "又无聊了吗", "啦啦啦啦啦啦"],
    "骚": ["你好骚呀", "太骚啦太骚啦", "烧晕啦"],
    "不要": ["哒咩达咩呀", "不要哇", "不要呀"],
    "生气": ["摸摸头啦", "生气会变丑啦", "别生气啦，我哄你"],
    "冲鸭": ["冲鸭冲鸭", "都跟着我冲呀", "往哪里冲鸭"],
    "冲呀": ["冲呀冲呀", "不顾一切向前冲呀", "怎么冲呀"],
    "来财": ["十年了，一毛财都没来", "哪里有财来呀", "再不来我就要被打啦"],
    "造孽": ["谁造的呢", "就是这么牛", "罪过，罪过"],
    "大水": ["大水爆两块五？", "洪水我都不去", "除非你上个广告"],
    "招人": ["又想嘎我腰子？", "一个月一万美金我就去", "黑人要不要"],
    "找工作": ["又想骗我路费了", "不如进厂包吃包住", "天天在这找，看你找了一年了"],
    "哦": ["否！", "哦哦～知道了", "哦你的头！"],
    "额": ["无语子～", "额…", "额尼玛的头！"],
    "鹅": ["鹅鹅鹅～", "铁锅炖大鹅？", "鹅你吗？"],
    "咦": ["咦~不要脸！", "咦个瘠薄！", "咦你奶奶的腿！"],
    "呜": ["哭什么？", "来我怀里吧宝～", "再呜我就亲你了！"],
    "嗨": ["臭嗨！", "嗨～", "你好呀！"],
    "你好": ["你好你好！", "我挺好的，你呢？", "你坏～"],
    "哈喽": ["哈喽哈喽！", "打完招呼就退下吧～", "嗨！"],
    "干嘛": ["不干嘛～", "想你了呀", "干就完了！"],
    "在干嘛": ["当然是在想你", "再跟宝宝聊天呢", "在当牛马啦"],
    "咋啦": ["咋啦宝子？", "没有咋啦～", "嘻嘻！"],
    "咋了": ["你想咋的？", "别惹我哦～", "抽你丫的！"],
    "哈哈": ["很好笑吗？", "哈你的头！", "流哈喇子了？"],
    "嘿嘿": ["真猥琐～", "死一边去嘿！", "再嘿就一巴掌！"],
    "呵呵": ["阴阳怪气的？", "我呵呵你～", "呵tui～！"],
    "嘻嘻": ["不跟你嘻嘻哈哈！", "嬉皮笑脸的～", "小屁孩！"],
    "滚": ["哼！不理你了！", "你才滚呢～", "滚去抱抱我！"],
    "哦豁": ["怎么滴？", "咋啦宝？", "我去～"],
    "嗯嗯": ["敷衍我？", "不理你了！", "嗯嗯对～"],
    "吃了": ["吃了什么呀", "好吃吗", "吃饱了没有呀"],
    "没吃": ["不饿吗", "怎么还没吃呢", "快去吃呀，别饿坏了"],
    "亲亲": ["mua～", "亲亲我的宝！", "😚"],
    "mua": ["mua~~mua"],
    "二手": ["可以去转转看看", "瓜子二手车，超便宜哦", "狗都不要~"],
    "么么": ["摸摸大～", "😘", "亲亲你！"],
    "嘴一个": ["亲一个！", "舌吻一下？", "舔舔～"],
    "摸摸": ["你要摸哪里？", "达咩达咩！", "不可以乱摸哦～"],
    "舔舔": ["你坏坏～", "不要哇！", "不要乱舔哇！"],
    "草": ["一种植物～", "卧槽！", "草谁？"],
    "操": ["操bb吗", "干瘠薄呀", "操咩啊"],
    "真的吗": ["当然是呀", "丁真的真", "真的不能再真了"],
    "尊嘟假嘟": ["尊嘟啦", "尊嘟捏", "又装可爱是吧"],
    "上班": ["已经在当牛马了", "不想上班了", "24小时上班，全年无休"],
    "买": ["买什么呢？", "买买买！", "给我买一个？"],
    "卖": ["卖U吗？", "卖煎饼咯～", "卖身救父？"],
    "炒群": ["跟我一起炒群吧！", "嘎嘎炒群～", "狠狠地炒！"],
    "超群": ["冲压，超群拉！", "今天也要加油炒群！", "猛猛超！"],
    "吵闹": ["真是吵闹～", "你不要哇哇叫！", "烦死个人！"],
    "哭了": ["来，摸摸头～", "我也哭了(假哭)", "哭唧唧～"],
    "醉了": ["喝了假酒吗？", "那我就要乘人之危了～", "嘿嘿嘿😈"],
    "奥耶": ["奥利给！", "耶斯！", "爽飞了～"],
    "熬夜": ["猝死了！", "伤身体～", "熬夜干什么？"],
    "外卖": ["点不起呀～", "我要喝冰美式！", "给我点？"],
    "笨蛋": ["你个小笨蛋～", "你真笨呐！", "笨死了！"],
    "叼毛": ["你个叼毛～", "你个二百五！", "说谁呢？"],
    "心疼": ["心疼你3秒～", "抱抱你！", "来我怀里～"],
    "宝宝": ["我在呢！", "我来啦～", "宝宝到！"],
    "抱抱": ["不要你～", "算了抱一下！", "亲亲！"],
    "无语": ["我也无语子～", "我的母语是无语", "乌鸡鲅鱼！"],
    "废了": ["确实废了～", "倒下了！", "没救了！"],
    "妈耶": ["我滴妈！", "何事如此惊慌？", "我勒个豆！"],
    "业绩": ["逼业绩也没有天天在这吹～", "有业绩吗叼毛？", "业绩0，又是电棍伺候！"],
    "任务": ["时间紧，任务重～", "完成了没有？", "任务是什么？"],
    "你是谁": ["我是小桃桃～", "我是你伟大的母亲！", "我是吃饭的宝贝！"],
    "你叫什么": ["我叫小桃桃～", "我叫桃宝！", "我叫小桃仙女！"],
    "你会什么": ["上天入地，无所不能！", "搬山填海，降妖伏魔～", "你能想到的我都会！"],
    "叫妈妈": ["倒反天罡？", "我是你妈妈！", "大逆不道！"],
    "叫爸爸": ["滚蛋！", "孩子你咋啦？", "你个龟孙！"],
    "小桃桃": ["来啦来啦！", "我在呢～", "怎么了宝子？"]
  },
  "mentioned_or_replied": [
    "怎么了嘛",
    "voice:myvoice.ogg",
    "好吧",
    "诶？",
    "emmmmmmm",
    "哇塞",
    "萨瓦迪卡",
    "我嘞个豆",
    "咋啦",
    "真不错呢",
    "嗦嘎",
    "然后捏",
    "说是这么说，但是。。",
    "那就酱吧",
    "你懂的啦",
    "笑死^_^",
    "啦啦啦",
    "我母鸡呀*^▽^*",
    "行吧行叭",
    "我滴孩呀",
    "我滴妈呀",
    "好好好",
    "嘿嘿",
    "嘻嘻"
  ],
  "fallback": [
  "我不懂",
  "额",
  "诶？",
  "扣你吉瓦？",
  "让我想想撒",
  "你想表达什么",
  "几个意思啊",
  "emmmmm",
  "搞什么呢",
  "你飘了啊",
  "给我整无语了",
  "妈耶",
  "咋啦这是",
  "啊？不是吧"
]
}
